{"coord": {"lon": -86.7844, "lat": 36.1659}, "weather": [{"id": 801, "main": "Clouds", "description": "few clouds", "icon": "02n"}], "base": "stations", "main": {"temp": 25.11, "feels_like": 25.9, "temp_min": 24.06, "temp_max": 25.77, "pressure": 1014, "humidity": 85, "sea_level": 1014, "grnd_level": 992}, "visibility": 10000, "wind": {"speed": 1.91, "deg": 224, "gust": 6.49}, "clouds": {"all": 24}, "dt": 1751350896, "sys": {"type": 2, "id": 47686, "country": "US", "sunrise": 1751366015, "sunset": 1751418493}, "timezone": -18000, "id": 4644585, "name": "Nashville", "cod": 200}